ImageLibrary/__init__.py
ImageLibrary/animations.py
ImageLibrary/compare_img.py
ImageLibrary/error_handler.py
ImageLibrary/errors.py
ImageLibrary/image_processor.py
ImageLibrary/imutils.py
ImageLibrary/keywords.py
ImageLibrary/main_window.py
ImageLibrary/open_cv.py
ImageLibrary/screenshot_operations.py
ImageLibrary/singleton.py
ImageLibrary/template.py
ImageLibrary/utils.py
ImageLibrary/values_iterator.py
ImageLibrary/window.py
ImageLibrary/window_function.py
ImageLibrary/zone.py
ImageLibrary/GUIProcess/__init__.py
ImageLibrary/GUIProcess/_gui_win.py
ImageLibrary/GUIProcess/_gui_x11.py
ImageLibrary/buttons/__init__.py
ImageLibrary/buttons/button.py
ImageLibrary/buttons/button_constructor.py
ImageLibrary/buttons/button_coord.py
ImageLibrary/buttons/buttons_panel.py
ImageLibrary/buttons/dynamic_button.py
ImageLibrary/buttons/global_button.py
ImageLibrary/buttons/multiple_button.py
ImageLibrary/buttons/static_button.py
ImageLibrary/libcore/__init__.py
ImageLibrary/libcore/librarycomponent.py
ImageLibrary/libcore/robotlibcore.py
robotframework_imagelibrary-1.0.1.dist-info/LICENSE
robotframework_imagelibrary-1.0.1.dist-info/METADATA
robotframework_imagelibrary-1.0.1.dist-info/WHEEL
robotframework_imagelibrary-1.0.1.dist-info/top_level.txt
robotframework_imagelibrary-1.0.1.dist-info/RECORD
