Metadata-Version: 2.1
Name: robotframework-imagelibrary
Version: 1.0.1
Summary: Image Processing Library For Robot Framework
Home-page: https://github.com/Simakvokka/robotframework-imagelibrary
Author: Prokhorova Maria
Author-email: msklenaj@gmail.com
License: Apache License 2.0
Keywords: robotframework testing testautomation image processing
Platform: Windows
Requires-Python: >3.5.*
Requires-Dist: robotframework
Requires-Dist: opencv-python
Requires-Dist: pyautogui
Requires-Dist: numpy
Requires-Dist: pytesseract
Requires-Dist: scikit-image
Requires-Dist: pillow
Requires-Dist: future
